Metadata-Version: 1.0
Name: nekogirl
Version: 0.0.6
Summary: An open source python package used to import nekogirl.
Home-page: https://github.com/mcwindy/nekogirl
Author: mcwindy
Author-email: chen_yuyang@outlook.com
License: WTFPL
Platform: UNKNOWN
